scarcity/__init__.py
scarcity/dashboard/__init__.py
scarcity/dashboard/auth.py
scarcity/dashboard/dependencies.py
scarcity/dashboard/registry.py
scarcity/dashboard/server.py
scarcity/dashboard/sockets.py
scarcity/dashboard/api/__init__.py
scarcity/dashboard/api/drg.py
scarcity/dashboard/api/federation.py
scarcity/dashboard/api/memory.py
scarcity/dashboard/api/meta.py
scarcity/dashboard/api/models.py
scarcity/dashboard/api/mpie.py
scarcity/dashboard/api/onboarding.py
scarcity/dashboard/api/simulation.py
scarcity/dashboard/api/status.py
scarcity/dashboard/api/telemetry.py
scarcity/dashboard/api/whatif.py
scarcity/dashboard/models/__init__.py
scarcity/dashboard/onboarding/__init__.py
scarcity/dashboard/onboarding/baskets.py
scarcity/dashboard/onboarding/clients.py
scarcity/dashboard/onboarding/domains.py
scarcity/dashboard/onboarding/gossip.py
scarcity/dashboard/onboarding/ingestion.py
scarcity/dashboard/onboarding/state.py
scarcity/engine/__init__.py
scarcity/engine/controller.py
scarcity/engine/encoder.py
scarcity/engine/engine.py
scarcity/engine/evaluator.py
scarcity/engine/exporter.py
scarcity/engine/resource_profile.py
scarcity/engine/store.py
scarcity/engine/types.py
scarcity/engine/utils.py
scarcity/engine/operators/__init__.py
scarcity/engine/operators/attention_ops.py
scarcity/engine/operators/causal_semantic_ops.py
scarcity/engine/operators/evaluation_ops.py
scarcity/engine/operators/integrative_ops.py
scarcity/engine/operators/relational_ops.py
scarcity/engine/operators/sketch_ops.py
scarcity/engine/operators/stability_ops.py
scarcity/engine/operators/structural_ops.py
scarcity/federation/__init__.py
scarcity/federation/aggregator.py
scarcity/federation/client_agent.py
scarcity/federation/codec.py
scarcity/federation/coordinator.py
scarcity/federation/packets.py
scarcity/federation/privacy_guard.py
scarcity/federation/reconciler.py
scarcity/federation/scheduler.py
scarcity/federation/transport.py
scarcity/federation/trust_scorer.py
scarcity-1.0.0.dist-info/licenses/LICENSE
scarcity-1.0.0.dist-info/METADATA
scarcity-1.0.0.dist-info/WHEEL
scarcity-1.0.0.dist-info/top_level.txt
scarcity-1.0.0.dist-info/RECORD
