Metadata-Version: 2.4
Name: scarcity
Version: 1.0.0
Summary: SCARCITY core simulation, federation, and governance library.
Author: Omega Makena
License-Expression: Apache-2.0
Project-URL: Homepage, https://example.com/scarcity
Requires-Python: >=3.9
License-File: LICENSE
Requires-Dist: numpy>=1.24
Provides-Extra: stream
Requires-Dist: pandas>=2.0; extra == "stream"
Requires-Dist: aiofiles>=23.2; extra == "stream"
Requires-Dist: websockets>=11.0; extra == "stream"
Requires-Dist: scikit-learn>=1.3; extra == "stream"
Provides-Extra: dashboard
Requires-Dist: fastapi>=0.110; extra == "dashboard"
Requires-Dist: uvicorn[standard]>=0.27; extra == "dashboard"
Requires-Dist: python-multipart>=0.0.9; extra == "dashboard"
Requires-Dist: pydantic>=2.6; extra == "dashboard"
Provides-Extra: gpu
Requires-Dist: torch>=2.1; extra == "gpu"
Requires-Dist: pytorch3d>=0.7; extra == "gpu"
Requires-Dist: pynvml>=11.0; extra == "gpu"
Provides-Extra: governor
Requires-Dist: psutil>=5.9; extra == "governor"
Provides-Extra: fmi
Requires-Dist: pyyaml>=6.0; extra == "fmi"
Requires-Dist: zstandard>=0.22; extra == "fmi"
Dynamic: license-file
